Metadata-Version: 2.1
Name: odoo13-addon-stock-picking-carrier-from-rule
Version: 13.0.1.0.1.dev4
Summary: Set the carrier on picking if the stock rule used has a partner address set with a delivery method.
Home-page: https://github.com/OCA/delivery-carrier
Author: Camptocamp, Odoo Community Association (OCA)
Author-email: support@odoo-community.org
License: AGPL-3
Platform: UNKNOWN
Classifier: Programming Language :: Python
Classifier: Framework :: Odoo
Classifier: Framework :: Odoo :: 13.0
Classifier: License :: OSI Approved :: GNU Affero General Public License v3
Requires-Python: >=3.5
Requires-Dist: odoo <13.1dev,>=13.0a
